starlette_web/__init__.py
starlette_web/common/__init__.py
starlette_web/common/app.py
starlette_web/common/authorization/__init__.py
starlette_web/common/authorization/backends.py
starlette_web/common/authorization/base_user.py
starlette_web/common/authorization/jwt_backend.py
starlette_web/common/authorization/jwt_utils.py
starlette_web/common/authorization/permissions.py
starlette_web/common/caches/__init__.py
starlette_web/common/caches/base.py
starlette_web/common/caches/base_lock.py
starlette_web/common/caches/cache_handler.py
starlette_web/common/caches/local_memory.py
starlette_web/common/channels/__init__.py
starlette_web/common/channels/base.py
starlette_web/common/channels/event.py
starlette_web/common/channels/exceptions.py
starlette_web/common/channels/layers/__init__.py
starlette_web/common/channels/layers/base.py
starlette_web/common/channels/layers/local_memory.py
starlette_web/common/conf/__init__.py
starlette_web/common/conf/app_manager.py
starlette_web/common/conf/base_app_config.py
starlette_web/common/conf/global_settings.py
starlette_web/common/conf/utils.py
starlette_web/common/database/__init__.py
starlette_web/common/database/columns.py
starlette_web/common/database/model_base.py
starlette_web/common/database/session_maker.py
starlette_web/common/database/types.py
starlette_web/common/email/__init__.py
starlette_web/common/email/base_sender.py
starlette_web/common/email/email_manager.py
starlette_web/common/email/smtp.py
starlette_web/common/files/__init__.py
starlette_web/common/files/cache.py
starlette_web/common/files/filelock.py
starlette_web/common/files/storages/__init__.py
starlette_web/common/files/storages/base.py
starlette_web/common/files/storages/filesystem.py
starlette_web/common/files/storages/storage_manager.py
starlette_web/common/http/__init__.py
starlette_web/common/http/base_endpoint.py
starlette_web/common/http/exception_handlers.py
starlette_web/common/http/exceptions.py
starlette_web/common/http/renderers.py
starlette_web-0.1.10.dist-info/LICENSE
starlette_web-0.1.10.dist-info/METADATA
starlette_web-0.1.10.dist-info/WHEEL
starlette_web-0.1.10.dist-info/entry_points.txt
starlette_web-0.1.10.dist-info/top_level.txt
starlette_web-0.1.10.dist-info/RECORD
