Metadata-Version: 2.1
Name: starlette-web
Version: 0.1.10
Summary: Asynchronous web framework, based on Starlette and inspired by Django
Author-email: Sergey Sayamov <dolamroth@mail.ru>, Dmitry Burnaev <dmitry.burnaev@gmail.com>
License: MIT
Project-URL: Homepage, https://github.com/dolamroth/starlette-web
Project-URL: Issues, https://github.com/dolamroth/starlette-web/issues
Classifier: Programming Language :: Python :: 3
Classifier: Programming Language :: Python :: 3 :: Only
Classifier: Programming Language :: Python :: 3.9
Classifier: Programming Language :: Python :: 3.10
Classifier: Programming Language :: Python :: 3.11
Classifier: Programming Language :: Python :: 3.12
Classifier: Programming Language :: Python :: 3.13
Classifier: License :: OSI Approved :: MIT License
Classifier: Development Status :: 2 - Pre-Alpha
Requires-Python: >=3.9
License-File: LICENSE
Requires-Dist: anyio (<4.7,>=4.6.0)
Requires-Dist: starlette (<1.0,>=0.39.0)
Requires-Dist: webargs-starlette (<2.2,>=2.1)
Requires-Dist: python-multipart (==0.0.10)
Requires-Dist: uvicorn[standard] (<0.31,>=0.30.6)
Requires-Dist: sqlalchemy (<2.1,>=2.0.35)
Requires-Dist: alembic (<1.14,>=1.13.3)
Requires-Dist: Jinja2 (<3.2,>=3.1)
Requires-Dist: httpx (<0.28,>=0.27.2)
Requires-Dist: python-dotenv (<0.22,>=0.21)
Requires-Dist: traceback-with-variables (<2.1,>=2.0.4)
Requires-Dist: aiosmtplib (<3.1,>=3.0.1)
Requires-Dist: filelock (<3.14,>=3.13.1)
Requires-Dist: marshmallow (<3.23,>=3.22.0)
Requires-Dist: chardet (<5.3,>=5.2.0)
Requires-Dist: PyJWT[crypto] (<2.10,>=2.9)
Requires-Dist: exceptiongroup (<2.0,>=1.2.2)
Provides-Extra: admin
Requires-Dist: starlette-admin (<0.12,>=0.11.2) ; extra == 'admin'
Provides-Extra: all
Requires-Dist: starlette-web[admin,apispec,auth,deploy,develop,mqtt,postgres,redis,scheduler,testing] ; extra == 'all'
Provides-Extra: apispec
Requires-Dist: apispec (<6.7,>=6.6.1) ; extra == 'apispec'
Requires-Dist: pyyaml (<6.1,>=6.0.1) ; extra == 'apispec'
Requires-Dist: openapi-spec-validator (<0.8,>=0.7.1) ; extra == 'apispec'
Provides-Extra: deploy
Requires-Dist: gunicorn (<24.0,>=23.0.0) ; extra == 'deploy'
Provides-Extra: develop
Requires-Dist: black (~=22.10.0) ; extra == 'develop'
Provides-Extra: full
Requires-Dist: starlette-web[all] ; extra == 'full'
Provides-Extra: mqtt
Requires-Dist: gmqtt (<0.7,>=0.6.13) ; extra == 'mqtt'
Provides-Extra: postgres
Requires-Dist: asyncpg (<0.30,>=0.29) ; extra == 'postgres'
Provides-Extra: redis
Requires-Dist: redis (<5.1,>=5.0.8) ; extra == 'redis'
Provides-Extra: scheduler
Requires-Dist: croniter (<2.1,>=2.0.1) ; extra == 'scheduler'
Requires-Dist: py-win-task-scheduler (==0.2.1) ; (sys_platform == "win32") and extra == 'scheduler'
Provides-Extra: ssh
Requires-Dist: asyncssh (<2.15,>=2.14.2) ; extra == 'ssh'
Provides-Extra: testing
Requires-Dist: pytest (>=8.3.3) ; extra == 'testing'
Requires-Dist: pytest-asyncio (>=0.24.0) ; extra == 'testing'
Requires-Dist: coverage (>=6.2) ; extra == 'testing'
Requires-Dist: psycopg2-binary (>=2.9) ; extra == 'testing'
Requires-Dist: requests (>=2.28) ; extra == 'testing'
Requires-Dist: flake8 (>=4.0) ; extra == 'testing'
